AIML_Bot-0.0.3.data/data/doc/aiml_bot/CHANGES.md
AIML_Bot-0.0.3.data/data/doc/aiml_bot/COPYING.txt
AIML_Bot-0.0.3.data/data/doc/aiml_bot/README.md
AIML_Bot-0.0.3.data/data/doc/aiml_bot/SUPPORTED_TAGS.md
AIML_Bot-0.0.3.data/data/doc/aiml_bot/TODO.md
AIML_Bot-0.0.3.dist-info/DESCRIPTION.rst
AIML_Bot-0.0.3.dist-info/METADATA
AIML_Bot-0.0.3.dist-info/RECORD
AIML_Bot-0.0.3.dist-info/WHEEL
AIML_Bot-0.0.3.dist-info/metadata.json
AIML_Bot-0.0.3.dist-info/top_level.txt
aiml_bot/__init__.py
aiml_bot/__main__.py
aiml_bot/aiml_parser.py
aiml_bot/bootstrap.aiml
aiml_bot/bot.py
aiml_bot/default_substitutions.py
aiml_bot/pattern_manager.py
aiml_bot/self-test.aiml
aiml_bot/tests.py
aiml_bot/utilities.py
aiml_bot/validate.py
aiml_bot/word_substitutions.py
