Metadata-Version: 2.0
Name: AIML-Bot
Version: 0.0.3
Summary: An interpreter package for AIML, the Artificial Intelligence Markup Language
Home-page: https://github.com/hosford42/aiml_bot
Author: Aaron Hosford
Author-email: hosford42@gmail.com
License: BSD-2-Clause
Platform: any
Classifier: Development Status :: 3 - Alpha
Classifier: Environment :: Console
Classifier: Intended Audience :: Developers
Classifier: Programming Language :: Python :: 3
Classifier: Operating System :: OS Independent
Classifier: Topic :: Communications :: Chat
Classifier: Topic :: Scientific/Engineering :: Artificial Intelligence
